gns3_proxy.py
gns3_proxy-0.8.data/scripts/gns3_proxy.py
gns3_proxy-0.8.dist-info/LICENSE
gns3_proxy-0.8.dist-info/METADATA
gns3_proxy-0.8.dist-info/WHEEL
gns3_proxy-0.8.dist-info/top_level.txt
gns3_proxy-0.8.dist-info/RECORD
